MANIFEST.in
account_asset_demo.xml
account_asset_invoice_view.xml
account_asset_view.xml
setup.py
./__init__.py
./__openerp__.py
./account_asset.py
./account_asset_invoice.py
./report/__init__.py
./report/account_asset_report.py
./wizard/__init__.py
./wizard/account_asset_change_duration.py
./wizard/wizard_asset_compute.py
i18n/account_asset.pot
i18n/ar.po
i18n/bs.po
i18n/ca.po
i18n/cs.po
i18n/da.po
i18n/de.po
i18n/en_GB.po
i18n/es.po
i18n/es_AR.po
i18n/es_CR.po
i18n/es_EC.po
i18n/es_MX.po
i18n/es_VE.po
i18n/et.po
i18n/fi.po
i18n/fr.po
i18n/fr_BE.po
i18n/gu.po
i18n/hr.po
i18n/hu.po
i18n/id.po
i18n/it.po
i18n/ja.po
i18n/ko.po
i18n/lt.po
i18n/mk.po
i18n/mn.po
i18n/nb.po
i18n/nl.po
i18n/nl_BE.po
i18n/pl.po
i18n/pt.po
i18n/pt_BR.po
i18n/ro.po
i18n/ru.po
i18n/sl.po
i18n/sr@latin.po
i18n/sv.po
i18n/th.po
i18n/tr.po
i18n/vi.po
i18n/zh_CN.po
i18n/zh_TW.po
openerp_account_asset.egg-info/PKG-INFO
openerp_account_asset.egg-info/SOURCES.txt
openerp_account_asset.egg-info/dependency_links.txt
openerp_account_asset.egg-info/requires.txt
openerp_account_asset.egg-info/top_level.txt
report/account_asset_report_view.xml
security/account_asset_security.xml
security/ir.model.access.csv
static/src/img/icon.png
test/account_asset.yml
test/account_asset_demo.yml
test/account_asset_wizard.yml
wizard/account_asset_change_duration_view.xml
wizard/wizard_asset_compute_view.xml